{
  "config": {
    "forbidOnly": false,
    "fullyParallel": false,
    "globalSetup": null,
    "globalTeardown": null,
    "globalTimeout": 0,
    "grep": {},
    "grepInvert": null,
    "maxFailures": 0,
    "metadata": {},
    "preserveOutput": "always",
    "projects": [
      {
        "outputDir": "C:/Users/atopcu/OneDrive - Amadeus Workplace/Desktop/PracticePlaywrigt/test-results",
        "repeatEach": 1,
        "retries": 0,
        "id": "",
        "name": "",
        "testDir": "C:/Users/atopcu/OneDrive - Amadeus Workplace/Desktop/PracticePlaywrigt",
        "testIgnore": [],
        "testMatch": [
          "tests/basicInteractions.spec.ts",
          "tests/example.spec.ts",
          "tests/alert.test.ts",
          "tests/dropdown.test.ts",
          "frame.test.ts",
          "calendar.test.ts",
          "uploadDownload.test.ts",
          "pomTest/addToCart.test.ts"
        ],
        "timeout": 30000
      }
    ],
    "reporter": [
      [
        "dot",
        null
      ],
      [
        "json",
        {
          "outputFile": "jsonReports/jsonReport.json"
        }
      ],
      [
        "html",
        {
          "open": "always"
        }
      ]
    ],
    "reportSlowTests": {
      "max": 5,
      "threshold": 15000
    },
    "configFile": "C:\\Users\\atopcu\\OneDrive - Amadeus Workplace\\Desktop\\PracticePlaywrigt\\playwright.config.ts",
    "rootDir": "C:/Users/atopcu/OneDrive - Amadeus Workplace/Desktop/PracticePlaywrigt",
    "quiet": false,
    "shard": null,
    "updateSnapshots": "missing",
    "version": "1.29.2",
    "workers": 10,
    "webServer": null
  },
  "suites": [
    {
      "title": "pomTest\\addToCart.test.ts",
      "file": "pomTest/addToCart.test.ts",
      "column": 0,
      "line": 0,
      "specs": [
        {
          "title": "Login test_002",
          "ok": false,
          "tags": [],
          "tests": [
            {
              "timeout": 30000,
              "annotations": [],
              "expectedStatus": "passed",
              "projectId": "",
              "projectName": "",
              "results": [
                {
                  "workerIndex": 0,
                  "status": "failed",
                  "duration": 10298,
                  "error": {
                    "message": "\u001b[2mexpect(\u001b[22m\u001b[31mreceived\u001b[39m\u001b[2m).\u001b[22mtoBe\u001b[2m(\u001b[22m\u001b[32mexpected\u001b[39m\u001b[2m) // Object.is equality\u001b[22m\n\nExpected: \u001b[32m\"My \"\u001b[39m\nReceived: \u001b[31m\"My \u001b[7mAccount\u001b[27m\"\u001b[39m",
                    "stack": "Error: \u001b[2mexpect(\u001b[22m\u001b[31mreceived\u001b[39m\u001b[2m).\u001b[22mtoBe\u001b[2m(\u001b[22m\u001b[32mexpected\u001b[39m\u001b[2m) // Object.is equality\u001b[22m\n\nExpected: \u001b[32m\"My \"\u001b[39m\nReceived: \u001b[31m\"My \u001b[7mAccount\u001b[27m\"\u001b[39m\n    at C:\\Users\\atopcu\\OneDrive - Amadeus Workplace\\Desktop\\PracticePlaywrigt\\pomTest\\addToCart.test.ts:42:32"
                  },
                  "errors": [
                    {
                      "location": {
                        "file": "C:\\Users\\atopcu\\OneDrive - Amadeus Workplace\\Desktop\\PracticePlaywrigt\\pomTest\\addToCart.test.ts",
                        "column": 32,
                        "line": 42
                      },
                      "message": "Error: \u001b[2mexpect(\u001b[22m\u001b[31mreceived\u001b[39m\u001b[2m).\u001b[22mtoBe\u001b[2m(\u001b[22m\u001b[32mexpected\u001b[39m\u001b[2m) // Object.is equality\u001b[22m\n\nExpected: \u001b[32m\"My \"\u001b[39m\nReceived: \u001b[31m\"My \u001b[7mAccount\u001b[27m\"\u001b[39m\n\n\u001b[90m   at \u001b[39mpomTest\\addToCart.test.ts:42\n\n\u001b[0m \u001b[90m 40 |\u001b[39m     \u001b[36mawait\u001b[39m page\u001b[33m.\u001b[39mwaitForTimeout(\u001b[35m3000\u001b[39m)\u001b[33m;\u001b[39m\u001b[0m\n\u001b[0m \u001b[90m 41 |\u001b[39m     console\u001b[33m.\u001b[39mlog(\u001b[33mHomePage\u001b[39m)\u001b[33m;\u001b[39m\u001b[0m\n\u001b[0m\u001b[31m\u001b[1m>\u001b[22m\u001b[39m\u001b[90m 42 |\u001b[39m     expect(\u001b[36mawait\u001b[39m page\u001b[33m.\u001b[39mtitle())\u001b[33m.\u001b[39mtoBe(\u001b[32m\"My \"\u001b[39m)\u001b[33m;\u001b[39m\u001b[0m\n\u001b[0m \u001b[90m    |\u001b[39m                                \u001b[31m\u001b[1m^\u001b[22m\u001b[39m\u001b[0m\n\u001b[0m \u001b[90m 43 |\u001b[39m })\u001b[0m\n\n\u001b[2m    at C:\\Users\\atopcu\\OneDrive - Amadeus Workplace\\Desktop\\PracticePlaywrigt\\pomTest\\addToCart.test.ts:42:32\u001b[22m"
                    }
                  ],
                  "stdout": [
                    {
                      "text": "\u001b[36m[class HomePage]\u001b[39m\n"
                    }
                  ],
                  "stderr": [],
                  "retry": 0,
                  "startTime": "2023-02-03T12:26:35.201Z",
                  "attachments": [
                    {
                      "name": "screenshot",
                      "contentType": "image/png",
                      "path": "C:\\Users\\atopcu\\OneDrive - Amadeus Workplace\\Desktop\\PracticePlaywrigt\\test-results\\pomTest-addToCart-Login-test-002\\test-failed-1.png"
                    }
                  ],
                  "errorLocation": {
                    "file": "C:\\Users\\atopcu\\OneDrive - Amadeus Workplace\\Desktop\\PracticePlaywrigt\\pomTest\\addToCart.test.ts",
                    "column": 32,
                    "line": 42
                  }
                }
              ],
              "status": "unexpected"
            }
          ],
          "id": "de488a82fdc52b0fe88f-651c9fc0809c157b89c5",
          "file": "pomTest/addToCart.test.ts",
          "line": 33,
          "column": 6
        }
      ]
    }
  ],
  "errors": []
}